AUTHORS
LICENSE
MANIFEST.in
README.rst
setup.py
templated_email/__init__.py
templated_email/models.py
templated_email/utils.py
templated_email/backends/__init__.py
templated_email/backends/mailchimp_sts.py
templated_email/backends/postageapp_backend.py
templated_email/backends/vanilla_django.py
vinta_django_templated_email.egg-info/PKG-INFO
vinta_django_templated_email.egg-info/SOURCES.txt
vinta_django_templated_email.egg-info/dependency_links.txt
vinta_django_templated_email.egg-info/requires.txt
vinta_django_templated_email.egg-info/top_level.txt