Metadata-Version: 1.1
Name: vinta-django-templated-email
Version: 0.5
Summary: A Django oriented templated / transaction email abstraction
Home-page: https://github.com/vintasoftware/django-templated-email
Author: Bradley Whittington
Author-email: radbrad182@gmail.com
License: MIT
Platform: any
Classifier: Development Status :: 5 - Production/Stable
Classifier: Intended Audience :: Developers
Classifier: License :: OSI Approved :: MIT License
Classifier: Operating System :: OS Independent
Classifier: Programming Language :: Python
Classifier: Topic :: Software Development :: Libraries :: Python Modules
Classifier: Framework :: Django
